odoo/addons/membership_product_set/README.rst
odoo/addons/membership_product_set/__init__.py
odoo/addons/membership_product_set/__manifest__.py
odoo/addons/membership_product_set/i18n/de.po
odoo/addons/membership_product_set/i18n/membership_product_set.pot
odoo/addons/membership_product_set/models/__init__.py
odoo/addons/membership_product_set/models/product_template.py
odoo/addons/membership_product_set/models/res_partner.py
odoo/addons/membership_product_set/static/description/icon.png
odoo/addons/membership_product_set/static/description/icon.svg
odoo/addons/membership_product_set/static/description/icon_main.svg
odoo/addons/membership_product_set/tests/__init__.py
odoo/addons/membership_product_set/tests/test_membership.py
odoo/addons/membership_product_set/views/product_template_views.xml
odoo11_addon_membership_product_set-11.0.1.0.0.99.dev2.dist-info/METADATA
odoo11_addon_membership_product_set-11.0.1.0.0.99.dev2.dist-info/WHEEL
odoo11_addon_membership_product_set-11.0.1.0.0.99.dev2.dist-info/top_level.txt
odoo11_addon_membership_product_set-11.0.1.0.0.99.dev2.dist-info/RECORD
